autoesda/__init__.py
autoesda/raster/__init__.py
autoesda/raster/controller.py
autoesda/raster/model.py
autoesda/vector/__init__.py
autoesda/vector/controller.py
autoesda/vector/model.py
autoesda-1.0.0.dist-info/LICENSE
autoesda-1.0.0.dist-info/METADATA
autoesda-1.0.0.dist-info/WHEEL
autoesda-1.0.0.dist-info/dependency_links.txt
autoesda-1.0.0.dist-info/top_level.txt
autoesda-1.0.0.dist-info/RECORD
