Metadata-Version: 2.1
Name: autoesda
Version: 1.0.0
Summary: A Python package that automates the exploratory spatial data analysis (ESDA) process by summarizing the results in an HTML report
Home-page: https://github.com/NicholasDeKock/autoesda
Author: Nicholas De Kock
Author-email: nicholas.dekock@tuks.co.za
License: BSD license
Keywords: autoesda
Classifier: Development Status :: 2 - Pre-Alpha
Classifier: Intended Audience :: Developers
Classifier: License :: OSI Approved :: BSD License
Classifier: Natural Language :: English
Classifier: Programming Language :: Python :: 3
Classifier: Programming Language :: Python :: 3.5
Classifier: Programming Language :: Python :: 3.6
Classifier: Programming Language :: Python :: 3.7
Classifier: Programming Language :: Python :: 3.8
Requires-Python: >=3.5
License-File: LICENSE
Requires-Dist: esda
Requires-Dist: geopandas ==0.8.1
Requires-Dist: libpysal ==4.4.0
Requires-Dist: matplotlib ==3.4.2
Requires-Dist: pysal ==2.3.0
Requires-Dist: seaborn ==0.11.2
Requires-Dist: splot >=1.1.4
